{"lastUsed":1625655357919,"path":"C:\/Users\/bfi\/eclipse-workspace","projectCount":16,"recentFiles":[{"path":"\/Kassabon\/src","parentWorkspace":"C:\/Users\/bfi\/eclipse-workspace","name":"main.java","lastModified":1625058679894},{"path":"\/Hello World\/src","parentWorkspace":"C:\/Users\/bfi\/eclipse-workspace","name":"HelloWorld.java","lastModified":1622026621313},{"path":"\/Deklarieren und Initialisieren von Variablen zu deiner Person\/src","parentWorkspace":"C:\/Users\/bfi\/eclipse-workspace","name":"main.java","lastModified":1622016988731},{"path":"\/rechnen\/src\/rechnen","parentWorkspace":"C:\/Users\/bfi\/eclipse-workspace","name":"main.java","lastModified":1622029478865},{"path":"\/verheiratet oder nicht\/src","parentWorkspace":"C:\/Users\/bfi\/eclipse-workspace","name":"main.java","lastModified":1625058679894},{"path":"\/einfache for schleifen\/src","parentWorkspace":"C:\/Users\/bfi\/eclipse-workspace","name":"main.java","lastModified":1622121717981,"locationURI":"file:\/C:\/Users\/bfi\/eclipse-workspace\/einfache%20for%20schleifen\/src\/main.java"},{"path":"\/Night Out\/src","parentWorkspace":"C:\/Users\/bfi\/eclipse-workspace","name":"main.java","lastModified":1625058679894,"locationURI":"file:\/C:\/Users\/bfi\/eclipse-workspace\/Night%20Out\/src\/main.java"},{"path":"\/Lebenslauf\/src","parentWorkspace":"C:\/Users\/bfi\/eclipse-workspace","name":"Main.java","lastModified":1622013691169},{"path":"\/javascript\/src\/javascript","parentWorkspace":"C:\/Users\/bfi\/eclipse-workspace","name":"main.java","lastModified":1623230863346,"locationURI":"file:\/C:\/Users\/bfi\/eclipse-workspace\/javascript\/src\/javascript\/main.java"},{"path":"\/Kalender\/src","parentWorkspace":"C:\/Users\/bfi\/eclipse-workspace","name":"main.java","lastModified":1625655389941,"locationURI":"file:\/C:\/Users\/bfi\/eclipse-workspace\/Kalender\/src\/main.java"},{"path":"\/Auto fahren\/src","parentWorkspace":"C:\/Users\/bfi\/eclipse-workspace","name":"main.java","lastModified":1622035794306},{"path":"\/1x1 mit Schleifen\/src","parentWorkspace":"C:\/Users\/bfi\/eclipse-workspace","name":"main.java","lastModified":1625058679465,"locationURI":"file:\/C:\/Users\/bfi\/eclipse-workspace\/1x1%20mit%20Schleifen\/src\/main.java"},{"path":"\/EinMalEins\/src","parentWorkspace":"C:\/Users\/bfi\/eclipse-workspace","name":"main.java","lastModified":1625058679894},{"path":"\/wir besuchen ein Festival\/src","parentWorkspace":"C:\/Users\/bfi\/eclipse-workspace","name":"main.java","lastModified":1624523386575},{"path":"\/Zahlen(t)räume mit if und Switch\/src","parentWorkspace":"C:\/Users\/bfi\/eclipse-workspace","name":"main.java","lastModified":1625058679894},{"path":"\/Gehen wir ins Kino\/src","parentWorkspace":"C:\/Users\/bfi\/eclipse-workspace","name":"main.java","lastModified":1624521934577,"locationURI":"file:\/C:\/Users\/bfi\/eclipse-workspace\/Gehen%20wir%20ins%20Kino\/src\/main.java"}]}